{
  "newspaper_id": "news-first-lk",
  "url": "https://www.newsfirst.lk/2022/06/17/diesel-distribution-begins-today-17/",
  "time_ut": 1655459940,
  "title": "Diesel distribution begins today (17)",
  "body_lines": [
    "COLOMBO (News 1st); The Ministry of Power & Energy noted that a vessel carrying 40,000 MT of Diesel arrived in the country on Thursday (16).",
    "An official at the Ministry of Power & Energy said that the distribution will commence on Friday (17).",
    "The Ministry of Power & Energy said that another few more vessel carrying fuel are scheduled to arrive in the country within the next few weeks.",
    "In the meantime, because of the shortage of Petrol and Diesel people are facing server difficulties.",
    "Many fuel queues were seen to be across the country for days to purchase fuel.",
    "News 1st correspondents said people are still waiting in lines with the hope of purchasing fuel.",
    "Fuel Crisis: President orders to streamline distribution; Army & STF to provide security to filling stations",
    "Army Commander vows to work for betterment of Nation in maiden troop address"
  ]
}