{
  "newspaper_id": "news-first-lk",
  "url": "https://www.newsfirst.lk/2022/06/11/two-dead-in-lunuwewa-drowning/",
  "time_ut": 1654960080,
  "title": "Two dead in Lunuwewa drowning",
  "body_lines": [
    "COLOMBO (News 1st);\u00a0Two young men died after drowning in the Lunu Wewa, in Thambuththegama.",
    "Police stated that the two men drowned when they were to bathing in the lake with a group this afternoon (11).",
    "The deceased have been identified as 18 and 23 year old residents of Ahungalla, Galle, and their\u00a0bodies are currently at the Thambuththegama Hospital.",
    "President denies CEB Chairman\u2019s claims on Wind Power Project to Adani",
    "Clean drinking water project, a relief for the people in Mannar",
    "China will not hesitate in providing relief to Sri Lankans: Ambassador"
  ]
}