{
  "newspaper_id": "news-first-lk",
  "url": "https://www.newsfirst.lk/2022/03/30/lorry-falls-off-dehiwala-fly-over/",
  "time_ut": 1648612020,
  "title": "Lorry falls off Dehiwala Fly-Over",
  "body_lines": [
    "COLOMBO (News 1st); Vehicular movement was disrupted due to an accident on the Dehiwala flyover on Wednesday (30) morning.",
    "The accident had taken place at around 3.30 this morning when a lorry traveling from Moratuwa to Colombo had collided with the security fence of the flyover and fell on to the road below.",
    "Sri Lanka will prevail & engineer rapid economic recovery; President tells BIMSTEC"
  ]
}