{
  "newspaper_id": "daily-ft-lk",
  "url": "https://www.ft.lk/news/SJB-not-ready-for-interim-Govt-with-President-and-PM-Rajitha/56-734073",
  "time_ut": 1651156020,
  "title": "SJB not ready for interim Govt. with President and PM : Rajitha",
  "body_lines": [
    "Samagi Jana Balawegaya (SJB) today said there are no plans of establishing an interim Government with President Gotabaya Rajapaksa at the helm.",
    "\u201cWe are prepared to form an interim Government only without the current Head of State and Prime Minister,\u201d SJB MP Rajitha Senarathne told journalists today."
  ]
}