{
  "newspaper_id": "ada-derana-lk",
  "url": "http://www.adaderana.lk/news/83024/special-train-services-for-poson-poya",
  "time_ut": 1655107020,
  "title": "Special train services for Poson Poya",
  "body_lines": [
    "The Department of Railways has taken steps to operate nine special trains from Colombo Fort to Anuradhapura for the upcoming Poson Poya.",
    "The special trains have been added to the service on the instructions of Transport and Highways Minister Bandula Gunawardena.",
    "Accordingly, the details of the train services are given below:"
  ]
}