{
  "newspaper_id": "ada-derana-lk",
  "url": "http://www.adaderana.lk/news/81315/another-man-standing-in-queue-dies-after-collapsing",
  "time_ut": 1647761040,
  "title": "Another man standing in queue dies after collapsing",
  "body_lines": [
    "Another man has died after collapsing while standing in a queue to purchase petrol in Kadawatha town, the police said.",
    "Meanwhile, 71-year-old died on Saturday (March 19) while waiting in a queue to obtain kerosene in the area of Wattegama, Kandy. The incident took place at the Ellepola filling station.",
    "The deceased was identified as a resident of Uduthalawinna area in Wattegama, named Mohamed Illiyas. It was reported that he had been in the queue for at least four hours and collapsed after getting drenched in the rain."
  ]
}