{
  "newspaper_id": "ada-derana-lk",
  "url": "http://www.adaderana.lk/news/82746/prime-minister-to-deliver-special-statement-today",
  "time_ut": 1653804120,
  "title": "Prime Minister to deliver special statement today",
  "body_lines": [
    "Prime Minister Ranil Wickremesinghe is scheduled to deliver a special statement today regarding the 21st Amendment to the Constitution and political reforms.",
    "The Premier\u2019s special statement will be telecast on TV Derana and Ada Derana 24 at 6.45 p.m. this evening (May 29)."
  ]
}