{
  "newspaper_id": "daily-mirror-lk",
  "url": "https://www.dailymirror.lk/breaking_news/35-busfare-hike-from-tonight-minimum-fare-will-increase-to-Rs-27/108-235265",
  "time_ut": 1650354480,
  "title": "35% busfare hike from tonight, minimum fare will increase to Rs.27",
  "body_lines": [
    "Following discussions with the Private Bus Owners' Associations today, a 35 per cent bus fare revision will come into effect from tonight.",
    "Today at the ministry, a discussion was held with Transport Minister Dilum Amugama and several private bus owners. (Chaturanga Samarawickrama)"
  ]
}