{
  "newspaper_id": "news-first-lk",
  "url": "https://www.newsfirst.lk/2022/05/10/controversial-malwana-mansion-torched-by-protestors/",
  "time_ut": 1652177100,
  "title": "Controversial Malwana mansion torched by protestors",
  "body_lines": [
    "COLOMBO (News 1st): The Malwana Residence belived to be owned by Ex-Minister Basil Rajapaksa was sent on fire by a group on Tuesday (10) afternoon.",
    "News 1st correspondents said that protestors first hurled stones as the residence and then breached the premises.",
    "It is reported that the Police Special Task Force was called in to control the situation"
  ]
}