{
  "newspaper_id": "ada-derana-lk",
  "url": "http://www.adaderana.lk/news/82787/pucsl-announces-power-cut-schedule-for-this-week",
  "time_ut": 1653992160,
  "title": "PUCSL announces power cut schedule for this week",
  "body_lines": [
    "The Public Utilities Commission of Sri Lanka (PUCSL) has approved the Ceylon Electricity Board\u2019s request for power interruptions from the 02nd to 05th of June, the chairman of electricity sector regulator Janaka Ratnayake says.",
    "The power cut duration has been reduced to a maximum of two hours, due to the prevailing low demand for electricity and the availability of hydropower generation.",
    "Demand Managmet Schedule-02nd and 03rd June 2022 by Ada Derana on Scribd",
    "Demand Managmet Schedule-04th June 2022 by Ada Derana on Scribd"
  ]
}