{
  "newspaper_id": "daily-mirror-lk",
  "url": "https://www.dailymirror.lk/breaking_news/Ruling-party-group-meeting-in-progress-at-Presidents-Office/108-234474",
  "time_ut": 1649077380,
  "title": "Ruling party group meeting in progress at President\u2019s Office",
  "body_lines": [
    "Ruling party group meeting is currently taking place at the President\u2019s Office with President Gotabaya Rajapaksa and Prime Minister Mahinda Rajapaksa chairing the meeting.",
    "A senior minister said that 132 MPs are attending the session in view to discuss the present crisis situation in-depth."
  ]
}