{
  "newspaper_id": "daily-mirror-lk",
  "url": "https://www.dailymirror.lk/breaking_news/MoD-appeals-public-to-notify-about-criminal-acts-by-mobs/108-236944",
  "time_ut": 1652399040,
  "title": "MoD appeals public to notify about criminal acts by mobs",
  "body_lines": [
    "The Ministry of Defence (MoD) has requested the general public to notify them with the details of criminal activities by mobs or violent groups and incidents of damaging of public and private properties, looting and assaults from any parts of the island.",
    "The Ministry said the public can provide such information through the following contact numbers:"
  ]
}