{
  "newspaper_id": "ada-derana-lk",
  "url": "http://www.adaderana.lk/news/82520/shipment-of-3500-mt-of-lp-gas-arrives-in-sri-lanka",
  "time_ut": 1652935620,
  "title": "Shipment of 3,500 MT of LP gas arrives in Sri Lanka",
  "body_lines": [
    "Another shipment of liquefied petroleum (LP) gas arrived in Sri Lanka, Litro Gas Lanka Limited says.",
    "According to the company\u2019s chairman Vijitha Herath, the payment for the shipment which contains approximately 3,500 metric tonnes of LP gas has been settled.",
    "He also stated that the unloading of the LP gas stock is hindered by the prevailing rough seas due to adverse weather.",
    "Meanwhile, two more vessels carrying 3,500 metric tonnes of LP gas each are expected to arrive in Sri Lanka in the coming week, the Litro Gas chairman added.",
    "Sri Lanka also received a shipment of 2,800 LP gas on Monday (May 16)."
  ]
}