{
  "newspaper_id": "ada-derana-lk",
  "url": "http://www.adaderana.lk/news/82432/public-requested-to-provide-information-on-those-who-looted-during-unrest",
  "time_ut": 1652530680,
  "title": "Public requested to provide information on those who looted during unrest",
  "body_lines": [
    "Sri Lanka Police has appealed to the general public to provide assistance to gather information on the damages caused to houses and other properties during the unrest that erupted across the country on the 9th of May.",
    "Accordingly, details of people, who looted houses and business places in the wake of the nationwide tensions, can be provided through the hotlines 1997 and 119.",
    "The police also assured witness protection and anonymity of those who provide such information."
  ]
}