{
  "newspaper_id": "news-first-lk",
  "url": "https://www.newsfirst.lk/2022/04/11/rupee-plunges-further-usd-at-rs-330/",
  "time_ut": 1649658780,
  "title": "Rupee plunges further, USD at Rs. 330/-",
  "body_lines": [
    "COLOMBO (News 1st); The selling price of the US dollar at licensed commercial banks had risen to Rs.330/- on Monday (11).",
    "The selling price of the British pound is Rs.431/- and the buying price is Rs.414/-.",
    "Galle \u2013 Matara Road blocked by protest against delayed gas supply",
    "Another Sri Lankan dies in fuel queue; 5th such death so far"
  ]
}