{
  "newspaper_id": "island-lk",
  "url": "http://island.lk/korean-ambassador-strengthens-economic-cooperation-with-sri-lanka/",
  "time_ut": 1648565760,
  "title": "Korean ambassador strengthens economic cooperation with Sri Lanka",
  "body_lines": [
    "Ambassador of Republic of Korea\u00a0Santhush Woonjin Jeong met with Minister of Finance . Basil Rajapaksa at the Finance Ministry.",
    "During the meeting held recently, ambassador Santhush and Finance Minister discussed issues of mutual interest, and looked forward to strengthening economic cooperation between the two countries as well as attracting investment opportunities for Korean companies in Sri Lanka.\u00a0 In addition, the two sides engaged on ways to expand labour cooperation, trade and investment cooperation and ODA support between Korea and Sri Lanka.",
    "Country Director of KOTRA, Lee Sung Hun and First Secretary of the Korean Embassy, Ms. Lim Miyeon joined the meeting.",
    "Rs. 5000 allowance for low income families seen as potentially destabilizing",
    "Leave a Reply Cancel replyYour email address will not be published. Required fields are marked *Comment Name *",
    "Save my name, email, and website in this browser for the next time I comment."
  ]
}