{
  "newspaper_id": "news-first-lk",
  "url": "https://www.newsfirst.lk/2022/03/21/pricehikemonday-bottled-water-prices-increased/",
  "time_ut": 1647840000,
  "title": "#PriceHikeMonday : Bottled Water prices increased",
  "body_lines": [
    "COLOMBO (News 1st); The Sri Lanka Water Bottle Manufacturers Associations aid that the price of bottled water has been increased due to the shortage of raw materials, fuel price hike, and the shortage of empty bottles.",
    "Accordingly, the price of a 1 1/2L water bottle has risen to Rs.120/- and a 5L water bottle is now Rs.300/-.",
    "Sri Lanka seeks US $ 1.5 Bn assistance from China, says Ambassador",
    "Charles Leclerc wins dramatic Bahrain F1 GP as Ferrari bring home one-two"
  ]
}