{
  "newspaper_id": "news-first-lk",
  "url": "https://www.newsfirst.lk/2022/05/03/sufficient-coal-imported-to-run-norochcholai-ceb/",
  "time_ut": 1651546380,
  "title": "Sufficient Coal imported to run Norochcholai: CEB",
  "body_lines": [
    "COLOMBO (News 1st): Sufficient stocks of Coal to run the Norochcholai Power Plant have been imported to the country as of now, the Ceylon Electricity Board (CEB) said.",
    "According to CEB Spokesperson Andrew Nawamani, two million metric tonnes of Coal were imported to the country from South Africa and Russia.",
    "The Coal reserves are sufficient to run the Norochcholai Power Plant until September this year, the CEB noted.",
    "Will introduce transparent fuel price formula for IOC & CEYPETCO: Energy Minister"
  ]
}